[
    {
        "client_msg_id": "9683ee92-4091-4c3b-ab6c-2befbfca5b31",
        "type": "message",
        "text": "Hey <@U028FAFCKGS> <@U029512CCV6> whoever wanted to do the validation of everything you should be good to do it on the book service, get that branch done and then make a pr to get it into develop",
        "user": "U0280JWD9AB",
        "ts": "1629765478.000700",
        "team": "T028U023WM7",
        "user_team": "T028U023WM7",
        "source_team": "T028U023WM7",
        "user_profile": {
            "avatar_hash": "6dd984ffcdcb",
            "image_72": "https:\/\/avatars.slack-edge.com\/2021-07-22\/2301122026195_6dd984ffcdcbf74e65a1_72.png",
            "first_name": "Maxwell",
            "real_name": "Maxwell Reid",
            "display_name": "Max",
            "team": "T028U023WM7",
            "name": "contact",
            "is_restricted": false,
            "is_ultra_restricted": false
        },
        "blocks": [
            {
                "type": "rich_text",
                "block_id": "Tb7G",
                "elements": [
                    {
                        "type": "rich_text_section",
                        "elements": [
                            {
                                "type": "text",
                                "text": "Hey "
                            },
                            {
                                "type": "user",
                                "user_id": "U028FAFCKGS"
                            },
                            {
                                "type": "text",
                                "text": " "
                            },
                            {
                                "type": "user",
                                "user_id": "U029512CCV6"
                            },
                            {
                                "type": "text",
                                "text": " whoever wanted to do the validation of everything you should be good to do it on the book service, get that branch done and then make a pr to get it into develop"
                            }
                        ]
                    }
                ]
            }
        ],
        "reactions": [
            {
                "name": "+1",
                "users": [
                    "U029512CCV6"
                ],
                "count": 1
            }
        ]
    },
    {
        "client_msg_id": "3a279eb7-b4a6-4be3-84f0-67e352a15e4e",
        "type": "message",
        "text": "book service branch*",
        "user": "U0280JWD9AB",
        "ts": "1629765606.001100",
        "team": "T028U023WM7",
        "user_team": "T028U023WM7",
        "source_team": "T028U023WM7",
        "user_profile": {
            "avatar_hash": "6dd984ffcdcb",
            "image_72": "https:\/\/avatars.slack-edge.com\/2021-07-22\/2301122026195_6dd984ffcdcbf74e65a1_72.png",
            "first_name": "Maxwell",
            "real_name": "Maxwell Reid",
            "display_name": "Max",
            "team": "T028U023WM7",
            "name": "contact",
            "is_restricted": false,
            "is_ultra_restricted": false
        },
        "blocks": [
            {
                "type": "rich_text",
                "block_id": "YoJy",
                "elements": [
                    {
                        "type": "rich_text_section",
                        "elements": [
                            {
                                "type": "text",
                                "text": "book service branch*"
                            }
                        ]
                    }
                ]
            }
        ]
    },
    {
        "client_msg_id": "7c579c7e-bc77-492b-b986-f2ad94e2f69a",
        "type": "message",
        "text": "its been pushed",
        "user": "U0280JWD9AB",
        "ts": "1629765608.001400",
        "team": "T028U023WM7",
        "user_team": "T028U023WM7",
        "source_team": "T028U023WM7",
        "user_profile": {
            "avatar_hash": "6dd984ffcdcb",
            "image_72": "https:\/\/avatars.slack-edge.com\/2021-07-22\/2301122026195_6dd984ffcdcbf74e65a1_72.png",
            "first_name": "Maxwell",
            "real_name": "Maxwell Reid",
            "display_name": "Max",
            "team": "T028U023WM7",
            "name": "contact",
            "is_restricted": false,
            "is_ultra_restricted": false
        },
        "blocks": [
            {
                "type": "rich_text",
                "block_id": "P9l",
                "elements": [
                    {
                        "type": "rich_text_section",
                        "elements": [
                            {
                                "type": "text",
                                "text": "its been pushed"
                            }
                        ]
                    }
                ]
            }
        ],
        "reactions": [
            {
                "name": "+1",
                "users": [
                    "U029512CCV6"
                ],
                "count": 1
            }
        ]
    },
    {
        "client_msg_id": "56d613cb-c645-4406-b928-5d45185e3cf5",
        "type": "message",
        "text": "could you send me the exact name of the branch you're referring to?",
        "user": "U029512CCV6",
        "ts": "1629765834.002000",
        "team": "T028U023WM7",
        "user_team": "T028U023WM7",
        "source_team": "T028U023WM7",
        "user_profile": {
            "avatar_hash": "dc3dba1c239b",
            "image_72": "https:\/\/avatars.slack-edge.com\/2021-07-18\/2300002178689_dc3dba1c239b262b6feb_72.jpg",
            "first_name": "",
            "real_name": "Sefanur Erciyas",
            "display_name": "Sefanur",
            "team": "T028U023WM7",
            "name": "sefanur.erciyas",
            "is_restricted": false,
            "is_ultra_restricted": false
        },
        "blocks": [
            {
                "type": "rich_text",
                "block_id": "M9FY",
                "elements": [
                    {
                        "type": "rich_text_section",
                        "elements": [
                            {
                                "type": "text",
                                "text": "could you send me the exact name of the branch you're referring to?"
                            }
                        ]
                    }
                ]
            }
        ]
    },
    {
        "client_msg_id": "e8a8f612-8be7-41bb-bcd7-d94a8b6edcec",
        "type": "message",
        "text": "its listed on the github page but its feat\/view-book-details-be-SM53",
        "user": "U0280JWD9AB",
        "ts": "1629765862.002400",
        "team": "T028U023WM7",
        "user_team": "T028U023WM7",
        "source_team": "T028U023WM7",
        "user_profile": {
            "avatar_hash": "6dd984ffcdcb",
            "image_72": "https:\/\/avatars.slack-edge.com\/2021-07-22\/2301122026195_6dd984ffcdcbf74e65a1_72.png",
            "first_name": "Maxwell",
            "real_name": "Maxwell Reid",
            "display_name": "Max",
            "team": "T028U023WM7",
            "name": "contact",
            "is_restricted": false,
            "is_ultra_restricted": false
        },
        "blocks": [
            {
                "type": "rich_text",
                "block_id": "UJ0aQ",
                "elements": [
                    {
                        "type": "rich_text_section",
                        "elements": [
                            {
                                "type": "text",
                                "text": "its listed on the github page but its feat\/view-book-details-be-SM53"
                            }
                        ]
                    }
                ]
            }
        ]
    },
    {
        "client_msg_id": "1a494241-f729-4f07-994a-f87abdc624a3",
        "type": "message",
        "text": "oh okay that branch, thanks",
        "user": "U029512CCV6",
        "ts": "1629765885.002700",
        "team": "T028U023WM7",
        "user_team": "T028U023WM7",
        "source_team": "T028U023WM7",
        "user_profile": {
            "avatar_hash": "dc3dba1c239b",
            "image_72": "https:\/\/avatars.slack-edge.com\/2021-07-18\/2300002178689_dc3dba1c239b262b6feb_72.jpg",
            "first_name": "",
            "real_name": "Sefanur Erciyas",
            "display_name": "Sefanur",
            "team": "T028U023WM7",
            "name": "sefanur.erciyas",
            "is_restricted": false,
            "is_ultra_restricted": false
        },
        "blocks": [
            {
                "type": "rich_text",
                "block_id": "BGe",
                "elements": [
                    {
                        "type": "rich_text_section",
                        "elements": [
                            {
                                "type": "text",
                                "text": "oh okay that branch, thanks"
                            }
                        ]
                    }
                ]
            }
        ]
    },
    {
        "client_msg_id": "b58f1e52-0fa4-4ebd-88c3-e70bfaf03b50",
        "type": "message",
        "text": "umm lol, okay docker:",
        "user": "U02951CDYSU",
        "ts": "1629775458.002900",
        "team": "T028U023WM7",
        "user_team": "T028U023WM7",
        "source_team": "T028U023WM7",
        "user_profile": {
            "avatar_hash": "ffa7a480c015",
            "image_72": "https:\/\/avatars.slack-edge.com\/2021-07-18\/2287356082482_ffa7a480c0158de4de4d_72.jpg",
            "first_name": "",
            "real_name": "Ewan Breakey",
            "display_name": "Ewan Breakey",
            "team": "T028U023WM7",
            "name": "ebreakey",
            "is_restricted": false,
            "is_ultra_restricted": false
        },
        "blocks": [
            {
                "type": "rich_text",
                "block_id": "mU35",
                "elements": [
                    {
                        "type": "rich_text_section",
                        "elements": [
                            {
                                "type": "text",
                                "text": "umm lol, okay docker:"
                            }
                        ]
                    }
                ]
            }
        ]
    },
    {
        "type": "message",
        "text": "",
        "files": [
            {
                "id": "F02BX9B9NAJ",
                "created": 1629775458,
                "timestamp": 1629775458,
                "name": "image.png",
                "title": "image.png",
                "mimetype": "image\/png",
                "filetype": "png",
                "pretty_type": "PNG",
                "user": "U02951CDYSU",
                "editable": false,
                "size": 65133,
                "mode": "hosted",
                "is_external": false,
                "external_type": "",
                "is_public": true,
                "public_url_shared": false,
                "display_as_bot": false,
                "username": "",
                "url_private": "https:\/\/files.slack.com\/files-pri\/T028U023WM7-F02BX9B9NAJ\/image.png?t=xoxe-2300002132721-2491962007047-2512898018532-73e6b43ec1fed45e8a8c9993e678c6c2",
                "url_private_download": "https:\/\/files.slack.com\/files-pri\/T028U023WM7-F02BX9B9NAJ\/download\/image.png?t=xoxe-2300002132721-2491962007047-2512898018532-73e6b43ec1fed45e8a8c9993e678c6c2",
                "thumb_64": "https:\/\/files.slack.com\/files-tmb\/T028U023WM7-F02BX9B9NAJ-486b90a2c4\/image_64.png?t=xoxe-2300002132721-2491962007047-2512898018532-73e6b43ec1fed45e8a8c9993e678c6c2",
                "thumb_80": "https:\/\/files.slack.com\/files-tmb\/T028U023WM7-F02BX9B9NAJ-486b90a2c4\/image_80.png?t=xoxe-2300002132721-2491962007047-2512898018532-73e6b43ec1fed45e8a8c9993e678c6c2",
                "thumb_360": "https:\/\/files.slack.com\/files-tmb\/T028U023WM7-F02BX9B9NAJ-486b90a2c4\/image_360.png?t=xoxe-2300002132721-2491962007047-2512898018532-73e6b43ec1fed45e8a8c9993e678c6c2",
                "thumb_360_w": 360,
                "thumb_360_h": 26,
                "thumb_480": "https:\/\/files.slack.com\/files-tmb\/T028U023WM7-F02BX9B9NAJ-486b90a2c4\/image_480.png?t=xoxe-2300002132721-2491962007047-2512898018532-73e6b43ec1fed45e8a8c9993e678c6c2",
                "thumb_480_w": 480,
                "thumb_480_h": 34,
                "thumb_160": "https:\/\/files.slack.com\/files-tmb\/T028U023WM7-F02BX9B9NAJ-486b90a2c4\/image_160.png?t=xoxe-2300002132721-2491962007047-2512898018532-73e6b43ec1fed45e8a8c9993e678c6c2",
                "thumb_720": "https:\/\/files.slack.com\/files-tmb\/T028U023WM7-F02BX9B9NAJ-486b90a2c4\/image_720.png?t=xoxe-2300002132721-2491962007047-2512898018532-73e6b43ec1fed45e8a8c9993e678c6c2",
                "thumb_720_w": 720,
                "thumb_720_h": 51,
                "thumb_800": "https:\/\/files.slack.com\/files-tmb\/T028U023WM7-F02BX9B9NAJ-486b90a2c4\/image_800.png?t=xoxe-2300002132721-2491962007047-2512898018532-73e6b43ec1fed45e8a8c9993e678c6c2",
                "thumb_800_w": 800,
                "thumb_800_h": 57,
                "thumb_960": "https:\/\/files.slack.com\/files-tmb\/T028U023WM7-F02BX9B9NAJ-486b90a2c4\/image_960.png?t=xoxe-2300002132721-2491962007047-2512898018532-73e6b43ec1fed45e8a8c9993e678c6c2",
                "thumb_960_w": 960,
                "thumb_960_h": 68,
                "thumb_1024": "https:\/\/files.slack.com\/files-tmb\/T028U023WM7-F02BX9B9NAJ-486b90a2c4\/image_1024.png?t=xoxe-2300002132721-2491962007047-2512898018532-73e6b43ec1fed45e8a8c9993e678c6c2",
                "thumb_1024_w": 1024,
                "thumb_1024_h": 73,
                "original_w": 1658,
                "original_h": 118,
                "thumb_tiny": "AwADADCmabTjTaZIU4\/dptOP3aADtR3\/AAo7Ud\/woA\/\/2Q==",
                "permalink": "https:\/\/septgrouphq.slack.com\/files\/U02951CDYSU\/F02BX9B9NAJ\/image.png",
                "permalink_public": "https:\/\/slack-files.com\/T028U023WM7-F02BX9B9NAJ-244b75be9f",
                "is_starred": false,
                "has_rich_preview": false
            }
        ],
        "upload": false,
        "user": "U02951CDYSU",
        "display_as_bot": false,
        "ts": "1629775461.003000",
        "reactions": [
            {
                "name": "exploding_head",
                "users": [
                    "U029512CCV6"
                ],
                "count": 1
            }
        ]
    },
    {
        "client_msg_id": "776fcafe-8a5a-4003-b8fb-b43a26949e86",
        "type": "message",
        "text": "apparently the images I just built were built 51 years ago",
        "user": "U02951CDYSU",
        "ts": "1629775479.003600",
        "team": "T028U023WM7",
        "user_team": "T028U023WM7",
        "source_team": "T028U023WM7",
        "user_profile": {
            "avatar_hash": "ffa7a480c015",
            "image_72": "https:\/\/avatars.slack-edge.com\/2021-07-18\/2287356082482_ffa7a480c0158de4de4d_72.jpg",
            "first_name": "",
            "real_name": "Ewan Breakey",
            "display_name": "Ewan Breakey",
            "team": "T028U023WM7",
            "name": "ebreakey",
            "is_restricted": false,
            "is_ultra_restricted": false
        },
        "blocks": [
            {
                "type": "rich_text",
                "block_id": "tdmK",
                "elements": [
                    {
                        "type": "rich_text_section",
                        "elements": [
                            {
                                "type": "text",
                                "text": "apparently the images I just built were built 51 years ago"
                            }
                        ]
                    }
                ]
            }
        ]
    }
]